epoc2etsi/__init__.py
epoc2etsi/namespaces.py
epoc2etsi/xml.py
epoc2etsi/forms/form1.py
epoc2etsi/forms/form2.py
epoc2etsi/forms/form3.py
epoc2etsi/forms/form5.py
epoc2etsi/forms/form6.py
epoc2etsi/forms/globalcaseid.py
epoc2etsi/forms/mappings.py
epoc2etsi/hi1/__init__.py
epoc2etsi/hi1/context.py
epoc2etsi/hi1/generators.py
epoc2etsi/hi1/helpers.py
epoc2etsi-0.1.4.dist-info/METADATA
epoc2etsi-0.1.4.dist-info/WHEEL
epoc2etsi-0.1.4.dist-info/entry_points.txt
epoc2etsi-0.1.4.dist-info/RECORD
