Metadata-Version: 2.4
Name: epoc2etsi
Version: 0.1.4
Summary: Add your description here
Author-email: mark <markc@tencastle.com>
Requires-Python: >=3.12
Requires-Dist: bitarray
Requires-Dist: lxml
